circuitml/__init__.py
circuitml/circuitml.py
circuitml/decisiontreeclassifier.py
circuitml/decisiontreeregressor.py
circuitml/gaussiannb.py
circuitml/linear_regression.py
circuitml/logisticregression.py
circuitml/pca.py
circuitml/platforms.py
circuitml/principalfft.py
circuitml/randomforestclassifier.py
circuitml/randomforestregressor.py
circuitml/rvm.py
circuitml/sefr.py
circuitml/svm.py
circuitml/utils.py
circuitml/wifiindoorpositioning.py
circuitml/xgboost.py
circuitml/templates/__init__.py
circuitml/templates/_skeleton.jinja
circuitml/templates/classmap.jinja
circuitml/templates/dot.jinja
circuitml/templates/testset.jinja
circuitml/templates/trainset.jinja
circuitml/templates/vote.jinja
circuitml/templates/__pycache__/__init__.cpython-37.pyc
circuitml/templates/decisiontree/__init__.py
circuitml/templates/decisiontree/decisiontree.jinja
circuitml/templates/decisiontree/decisiontree_regressor.jinja
circuitml/templates/decisiontree/tree.jinja
circuitml/templates/decisiontree/tree_regressor.jinja
circuitml/templates/gaussiannb/__init__.py
circuitml/templates/gaussiannb/gaussiannb.jinja
circuitml/templates/gaussiannb/vote.jinja
circuitml/templates/linearregression/__init__.py
circuitml/templates/linearregression/linearregression.jinja
circuitml/templates/logisticregression/__init__.py
circuitml/templates/logisticregression/logisticregression.jinja
circuitml/templates/logisticregression/vote.arduino.jinja
circuitml/templates/logisticregression/vote.attiny.jinja
circuitml/templates/pca/__init__.py
circuitml/templates/pca/pca.jinja
circuitml/templates/principalfft/__init__.py
circuitml/templates/principalfft/lut.jinja
circuitml/templates/principalfft/lut_bool.jinja
circuitml/templates/principalfft/principalfft.jinja
circuitml/templates/randomforest/__init__.py
circuitml/templates/randomforest/randomforest.jinja
circuitml/templates/randomforest/randomforest_regressor.jinja
circuitml/templates/randomforest/tree.jinja
circuitml/templates/randomforest/tree_regressor.jinja
circuitml-1.0.dist-info/LICENSE
circuitml-1.0.dist-info/METADATA
circuitml-1.0.dist-info/WHEEL
circuitml-1.0.dist-info/top_level.txt
circuitml-1.0.dist-info/RECORD
